{
  "Umuahia, Abia, Nigeria": {
    "timestamp": 1779262411.7587833,
    "data": {
      "max_rain_prob": 95,
      "risk_level": "HIGH"
    }
  },
  "Uyo, Akwa Ibom, Nigeria": {
    "timestamp": 1779262412.3957503,
    "data": {
      "max_rain_prob": 84,
      "risk_level": "HIGH"
    }
  },
  "Yola, Adamawa, Nigeria": {
    "timestamp": 1779262413.0301197,
    "data": {
      "max_rain_prob": 7,
      "risk_level": "LOW"
    }
  },
  "Awka, Anambra, Nigeria": {
    "timestamp": 1779262413.1963735,
    "data": {
      "max_rain_prob": 70,
      "risk_level": "HIGH"
    }
  },
  "Yenagoa, Bayelsa, Nigeria": {
    "timestamp": 1779262413.8611023,
    "data": {
      "max_rain_prob": 83,
      "risk_level": "HIGH"
    }
  },
  "Makurdi, Benue, Nigeria": {
    "timestamp": 1779262414.5050466,
    "data": {
      "max_rain_prob": 0,
      "risk_level": "LOW"
    }
  },
  "Calabar, Cross River, Nigeria": {
    "timestamp": 1779262415.1458225,
    "data": {
      "max_rain_prob": 75,
      "risk_level": "HIGH"
    }
  },
  "Asaba, Delta, Nigeria": {
    "timestamp": 1779262415.7786078,
    "data": {
      "max_rain_prob": 75,
      "risk_level": "HIGH"
    }
  },
  "Benin City, Edo, Nigeria": {
    "timestamp": 1779262416.2678251,
    "data": {
      "max_rain_prob": 99,
      "risk_level": "HIGH"
    }
  },
  "Ado Ekiti, Ekiti, Nigeria": {
    "timestamp": 1779262416.8993793,
    "data": {
      "max_rain_prob": 78,
      "risk_level": "HIGH"
    }
  },
  "Enugu, Enugu, Nigeria": {
    "timestamp": 1779262417.5348783,
    "data": {
      "max_rain_prob": 47,
      "risk_level": "MODERATE"
    }
  },
  "Dutse, Jigawa, Nigeria": {
    "timestamp": 1779262418.1681623,
    "data": {
      "max_rain_prob": 0,
      "risk_level": "LOW"
    }
  },
  "Kaduna, Kaduna, Nigeria": {
    "timestamp": 1779262418.7989779,
    "data": {
      "max_rain_prob": 50,
      "risk_level": "MODERATE"
    }
  },
  "Kano, Kano, Nigeria": {
    "timestamp": 1779262419.4354289,
    "data": {
      "max_rain_prob": 0,
      "risk_level": "LOW"
    }
  },
  "Birnin Kebbi, Kebbi, Nigeria": {
    "timestamp": 1779262420.086072,
    "data": {
      "max_rain_prob": 0,
      "risk_level": "LOW"
    }
  },
  "Lokoja, Kogi, Nigeria": {
    "timestamp": 1779262420.7305243,
    "data": {
      "max_rain_prob": 7,
      "risk_level": "LOW"
    }
  },
  "Ilorin, Kwara, Nigeria": {
    "timestamp": 1779262421.364772,
    "data": {
      "max_rain_prob": 12,
      "risk_level": "LOW"
    }
  },
  "Ikeja, Lagos, Nigeria": {
    "timestamp": 1779262421.9946523,
    "data": {
      "max_rain_prob": 66,
      "risk_level": "MODERATE"
    }
  },
  "Owerri, Imo, Nigeria": {
    "timestamp": 1779262422.6365056,
    "data": {
      "max_rain_prob": 96,
      "risk_level": "HIGH"
    }
  },
  "Abeokuta, Ogun, Nigeria": {
    "timestamp": 1779262423.255371,
    "data": {
      "max_rain_prob": 75,
      "risk_level": "HIGH"
    }
  },
  "Sagamu, Ogun State, Nigeria": {
    "timestamp": 1779262423.8906062,
    "data": {
      "max_rain_prob": 73,
      "risk_level": "HIGH"
    }
  },
  "Akure, Ondo, Nigeria": {
    "timestamp": 1779262424.5374346,
    "data": {
      "max_rain_prob": 100,
      "risk_level": "HIGH"
    }
  },
  "Osogbo, Osun, Nigeria": {
    "timestamp": 1779262425.1731267,
    "data": {
      "max_rain_prob": 67,
      "risk_level": "MODERATE"
    }
  },
  "Jos, Plateau, Nigeria": {
    "timestamp": 1779262425.7991254,
    "data": {
      "max_rain_prob": 21,
      "risk_level": "LOW"
    }
  },
  "Port Harcourt, Rivers, Nigeria": {
    "timestamp": 1779262426.441228,
    "data": {
      "max_rain_prob": 64,
      "risk_level": "MODERATE"
    }
  },
  "Ibadan, Oyo, Nigeria": {
    "timestamp": 1779262427.085952,
    "data": {
      "max_rain_prob": 72,
      "risk_level": "HIGH"
    }
  },
  "Jalingo, Taraba, Nigeria": {
    "timestamp": 1779262427.7143853,
    "data": {
      "max_rain_prob": 0,
      "risk_level": "LOW"
    }
  }
}