{
  "Umuahia, Abia, Nigeria": {
    "timestamp": 1777967460.2526684,
    "data": {
      "max_rain_prob": 98,
      "risk_level": "HIGH"
    }
  },
  "Uyo, Akwa Ibom, Nigeria": {
    "timestamp": 1777967460.4027295,
    "data": {
      "max_rain_prob": 87,
      "risk_level": "HIGH"
    }
  },
  "Yola, Adamawa, Nigeria": {
    "timestamp": 1777967460.5389476,
    "data": {
      "max_rain_prob": 0,
      "risk_level": "LOW"
    }
  },
  "Awka, Anambra, Nigeria": {
    "timestamp": 1777967460.6864157,
    "data": {
      "max_rain_prob": 57,
      "risk_level": "MODERATE"
    }
  },
  "Yenagoa, Bayelsa, Nigeria": {
    "timestamp": 1777967460.8235896,
    "data": {
      "max_rain_prob": 92,
      "risk_level": "HIGH"
    }
  },
  "Makurdi, Benue, Nigeria": {
    "timestamp": 1777967460.9586825,
    "data": {
      "max_rain_prob": 0,
      "risk_level": "LOW"
    }
  },
  "Calabar, Cross River, Nigeria": {
    "timestamp": 1777967461.1159954,
    "data": {
      "max_rain_prob": 93,
      "risk_level": "HIGH"
    }
  },
  "Asaba, Delta, Nigeria": {
    "timestamp": 1777967461.259885,
    "data": {
      "max_rain_prob": 66,
      "risk_level": "MODERATE"
    }
  },
  "Benin City, Edo, Nigeria": {
    "timestamp": 1777967461.4020214,
    "data": {
      "max_rain_prob": 95,
      "risk_level": "HIGH"
    }
  },
  "Ado Ekiti, Ekiti, Nigeria": {
    "timestamp": 1777967461.5363646,
    "data": {
      "max_rain_prob": 68,
      "risk_level": "MODERATE"
    }
  },
  "Enugu, Enugu, Nigeria": {
    "timestamp": 1777967461.6808238,
    "data": {
      "max_rain_prob": 39,
      "risk_level": "LOW"
    }
  },
  "Dutse, Jigawa, Nigeria": {
    "timestamp": 1777967461.8292203,
    "data": {
      "max_rain_prob": 0,
      "risk_level": "LOW"
    }
  },
  "Kaduna, Kaduna, Nigeria": {
    "timestamp": 1777967461.9816146,
    "data": {
      "max_rain_prob": 0,
      "risk_level": "LOW"
    }
  },
  "Kano, Kano, Nigeria": {
    "timestamp": 1777967462.115341,
    "data": {
      "max_rain_prob": 0,
      "risk_level": "LOW"
    }
  },
  "Birnin Kebbi, Kebbi, Nigeria": {
    "timestamp": 1777967462.258816,
    "data": {
      "max_rain_prob": 0,
      "risk_level": "LOW"
    }
  },
  "Lokoja, Kogi, Nigeria": {
    "timestamp": 1777967462.4202688,
    "data": {
      "max_rain_prob": 3,
      "risk_level": "LOW"
    }
  },
  "Ilorin, Kwara, Nigeria": {
    "timestamp": 1777967462.557353,
    "data": {
      "max_rain_prob": 31,
      "risk_level": "LOW"
    }
  },
  "Ikeja, Lagos, Nigeria": {
    "timestamp": 1777967462.7113605,
    "data": {
      "max_rain_prob": 32,
      "risk_level": "LOW"
    }
  },
  "Owerri, Imo, Nigeria": {
    "timestamp": 1777967462.8573847,
    "data": {
      "max_rain_prob": 100,
      "risk_level": "HIGH"
    }
  },
  "Abeokuta, Ogun, Nigeria": {
    "timestamp": 1777967463.0033004,
    "data": {
      "max_rain_prob": 63,
      "risk_level": "MODERATE"
    }
  },
  "Sagamu, Ogun State, Nigeria": {
    "timestamp": 1777967463.152492,
    "data": {
      "max_rain_prob": 53,
      "risk_level": "MODERATE"
    }
  },
  "Akure, Ondo, Nigeria": {
    "timestamp": 1777967463.3720825,
    "data": {
      "max_rain_prob": 86,
      "risk_level": "HIGH"
    }
  },
  "Osogbo, Osun, Nigeria": {
    "timestamp": 1777967463.5079336,
    "data": {
      "max_rain_prob": 87,
      "risk_level": "HIGH"
    }
  },
  "Jos, Plateau, Nigeria": {
    "timestamp": 1777967463.6539395,
    "data": {
      "max_rain_prob": 0,
      "risk_level": "LOW"
    }
  },
  "Port Harcourt, Rivers, Nigeria": {
    "timestamp": 1777967463.80194,
    "data": {
      "max_rain_prob": 81,
      "risk_level": "HIGH"
    }
  },
  "Ibadan, Oyo, Nigeria": {
    "timestamp": 1777967463.9414184,
    "data": {
      "max_rain_prob": 79,
      "risk_level": "HIGH"
    }
  },
  "Jalingo, Taraba, Nigeria": {
    "timestamp": 1777967464.0913165,
    "data": {
      "max_rain_prob": 31,
      "risk_level": "LOW"
    }
  }
}