{
  "Umuahia, Abia, Nigeria": {
    "timestamp": 1773074674.9025207,
    "data": {
      "max_rain_prob": 14,
      "risk_level": "LOW"
    }
  },
  "Uyo, Akwa Ibom, Nigeria": {
    "timestamp": 1773074675.098674,
    "data": {
      "max_rain_prob": 28,
      "risk_level": "LOW"
    }
  },
  "Yola, Adamawa, Nigeria": {
    "timestamp": 1773074675.2878237,
    "data": {
      "max_rain_prob": 0,
      "risk_level": "LOW"
    }
  },
  "Awka, Anambra, Nigeria": {
    "timestamp": 1773074675.4831524,
    "data": {
      "max_rain_prob": 4,
      "risk_level": "LOW"
    }
  },
  "Yenagoa, Bayelsa, Nigeria": {
    "timestamp": 1773074675.6432989,
    "data": {
      "max_rain_prob": 99,
      "risk_level": "HIGH"
    }
  },
  "Makurdi, Benue, Nigeria": {
    "timestamp": 1773074675.8215802,
    "data": {
      "max_rain_prob": 0,
      "risk_level": "LOW"
    }
  },
  "Calabar, Cross River, Nigeria": {
    "timestamp": 1773074675.9903166,
    "data": {
      "max_rain_prob": 46,
      "risk_level": "MODERATE"
    }
  },
  "Asaba, Delta, Nigeria": {
    "timestamp": 1773074676.156891,
    "data": {
      "max_rain_prob": 12,
      "risk_level": "LOW"
    }
  },
  "Benin City, Edo, Nigeria": {
    "timestamp": 1773074676.3286421,
    "data": {
      "max_rain_prob": 26,
      "risk_level": "LOW"
    }
  },
  "Ado Ekiti, Ekiti, Nigeria": {
    "timestamp": 1773074676.492112,
    "data": {
      "max_rain_prob": 39,
      "risk_level": "LOW"
    }
  },
  "Enugu, Enugu, Nigeria": {
    "timestamp": 1773074676.664742,
    "data": {
      "max_rain_prob": 0,
      "risk_level": "LOW"
    }
  },
  "Dutse, Jigawa, Nigeria": {
    "timestamp": 1773074676.8582163,
    "data": {
      "max_rain_prob": 0,
      "risk_level": "LOW"
    }
  },
  "Kaduna, Kaduna, Nigeria": {
    "timestamp": 1773074677.0328383,
    "data": {
      "max_rain_prob": 0,
      "risk_level": "LOW"
    }
  },
  "Kano, Kano, Nigeria": {
    "timestamp": 1773074677.2042708,
    "data": {
      "max_rain_prob": 0,
      "risk_level": "LOW"
    }
  },
  "Birnin Kebbi, Kebbi, Nigeria": {
    "timestamp": 1773074677.3746583,
    "data": {
      "max_rain_prob": 0,
      "risk_level": "LOW"
    }
  },
  "Lokoja, Kogi, Nigeria": {
    "timestamp": 1773074677.546956,
    "data": {
      "max_rain_prob": 0,
      "risk_level": "LOW"
    }
  },
  "Ilorin, Kwara, Nigeria": {
    "timestamp": 1773074677.714547,
    "data": {
      "max_rain_prob": 0,
      "risk_level": "LOW"
    }
  },
  "Ikeja, Lagos, Nigeria": {
    "timestamp": 1773074677.889377,
    "data": {
      "max_rain_prob": 55,
      "risk_level": "MODERATE"
    }
  },
  "Owerri, Imo, Nigeria": {
    "timestamp": 1773074678.057656,
    "data": {
      "max_rain_prob": 39,
      "risk_level": "LOW"
    }
  },
  "Abeokuta, Ogun, Nigeria": {
    "timestamp": 1773074678.2264426,
    "data": {
      "max_rain_prob": 55,
      "risk_level": "MODERATE"
    }
  },
  "Sagamu, Ogun State, Nigeria": {
    "timestamp": 1773074678.390383,
    "data": {
      "max_rain_prob": 51,
      "risk_level": "MODERATE"
    }
  },
  "Akure, Ondo, Nigeria": {
    "timestamp": 1773074678.5529168,
    "data": {
      "max_rain_prob": 24,
      "risk_level": "LOW"
    }
  },
  "Osogbo, Osun, Nigeria": {
    "timestamp": 1773074678.718128,
    "data": {
      "max_rain_prob": 21,
      "risk_level": "LOW"
    }
  },
  "Jos, Plateau, Nigeria": {
    "timestamp": 1773074678.8895082,
    "data": {
      "max_rain_prob": 0,
      "risk_level": "LOW"
    }
  },
  "Port Harcourt, Rivers, Nigeria": {
    "timestamp": 1773074679.0668771,
    "data": {
      "max_rain_prob": 87,
      "risk_level": "HIGH"
    }
  },
  "Ibadan, Oyo, Nigeria": {
    "timestamp": 1773074679.2379951,
    "data": {
      "max_rain_prob": 33,
      "risk_level": "LOW"
    }
  },
  "Jalingo, Taraba, Nigeria": {
    "timestamp": 1773074679.416703,
    "data": {
      "max_rain_prob": 0,
      "risk_level": "LOW"
    }
  }
}