{
  "Umuahia, Abia, Nigeria": {
    "timestamp": 1771193571.8008795,
    "data": {
      "max_rain_prob": 8,
      "risk_level": "LOW"
    }
  },
  "Uyo, Akwa Ibom, Nigeria": {
    "timestamp": 1771193572.0918891,
    "data": {
      "max_rain_prob": 4,
      "risk_level": "LOW"
    }
  },
  "Yola, Adamawa, Nigeria": {
    "timestamp": 1771193572.3476245,
    "data": {
      "max_rain_prob": 0,
      "risk_level": "LOW"
    }
  },
  "Awka, Anambra, Nigeria": {
    "timestamp": 1771193572.6245432,
    "data": {
      "max_rain_prob": 6,
      "risk_level": "LOW"
    }
  },
  "Yenagoa, Bayelsa, Nigeria": {
    "timestamp": 1771193572.9034915,
    "data": {
      "max_rain_prob": 32,
      "risk_level": "LOW"
    }
  },
  "Makurdi, Benue, Nigeria": {
    "timestamp": 1771193573.162576,
    "data": {
      "max_rain_prob": 0,
      "risk_level": "LOW"
    }
  },
  "Calabar, Cross River, Nigeria": {
    "timestamp": 1771193573.4524841,
    "data": {
      "max_rain_prob": 24,
      "risk_level": "LOW"
    }
  },
  "Asaba, Delta, Nigeria": {
    "timestamp": 1771193573.7573578,
    "data": {
      "max_rain_prob": 13,
      "risk_level": "LOW"
    }
  },
  "Benin City, Edo, Nigeria": {
    "timestamp": 1771193574.0731492,
    "data": {
      "max_rain_prob": 4,
      "risk_level": "LOW"
    }
  },
  "Ado Ekiti, Ekiti, Nigeria": {
    "timestamp": 1771193574.3766613,
    "data": {
      "max_rain_prob": 0,
      "risk_level": "LOW"
    }
  },
  "Enugu, Enugu, Nigeria": {
    "timestamp": 1771193574.632134,
    "data": {
      "max_rain_prob": 0,
      "risk_level": "LOW"
    }
  },
  "Dutse, Jigawa, Nigeria": {
    "timestamp": 1771193574.8878603,
    "data": {
      "max_rain_prob": 0,
      "risk_level": "LOW"
    }
  },
  "Kaduna, Kaduna, Nigeria": {
    "timestamp": 1771193575.2015085,
    "data": {
      "max_rain_prob": 0,
      "risk_level": "LOW"
    }
  },
  "Kano, Kano, Nigeria": {
    "timestamp": 1771193575.5175686,
    "data": {
      "max_rain_prob": 0,
      "risk_level": "LOW"
    }
  },
  "Birnin Kebbi, Kebbi, Nigeria": {
    "timestamp": 1771193575.8095188,
    "data": {
      "max_rain_prob": 0,
      "risk_level": "LOW"
    }
  },
  "Lokoja, Kogi, Nigeria": {
    "timestamp": 1771193576.0906482,
    "data": {
      "max_rain_prob": 0,
      "risk_level": "LOW"
    }
  },
  "Ilorin, Kwara, Nigeria": {
    "timestamp": 1771193576.3407764,
    "data": {
      "max_rain_prob": 0,
      "risk_level": "LOW"
    }
  },
  "Ikeja, Lagos, Nigeria": {
    "timestamp": 1771193576.6250334,
    "data": {
      "max_rain_prob": 0,
      "risk_level": "LOW"
    }
  },
  "Owerri, Imo, Nigeria": {
    "timestamp": 1771193576.9097862,
    "data": {
      "max_rain_prob": 19,
      "risk_level": "LOW"
    }
  },
  "Abeokuta, Ogun, Nigeria": {
    "timestamp": 1771193577.2048025,
    "data": {
      "max_rain_prob": 0,
      "risk_level": "LOW"
    }
  },
  "Sagamu, Ogun State, Nigeria": {
    "timestamp": 1771193577.4563386,
    "data": {
      "max_rain_prob": 0,
      "risk_level": "LOW"
    }
  },
  "Akure, Ondo, Nigeria": {
    "timestamp": 1771193577.7295015,
    "data": {
      "max_rain_prob": 0,
      "risk_level": "LOW"
    }
  },
  "Osogbo, Osun, Nigeria": {
    "timestamp": 1771193578.0165584,
    "data": {
      "max_rain_prob": 0,
      "risk_level": "LOW"
    }
  },
  "Jos, Plateau, Nigeria": {
    "timestamp": 1771193578.305255,
    "data": {
      "max_rain_prob": 0,
      "risk_level": "LOW"
    }
  },
  "Port Harcourt, Rivers, Nigeria": {
    "timestamp": 1771193578.5980518,
    "data": {
      "max_rain_prob": 24,
      "risk_level": "LOW"
    }
  },
  "Ibadan, Oyo, Nigeria": {
    "timestamp": 1771193578.8568223,
    "data": {
      "max_rain_prob": 0,
      "risk_level": "LOW"
    }
  },
  "Jalingo, Taraba, Nigeria": {
    "timestamp": 1771193579.1460364,
    "data": {
      "max_rain_prob": 0,
      "risk_level": "LOW"
    }
  }
}