{
  "Umuahia, Abia, Nigeria": {
    "timestamp": 1773931222.1075075,
    "data": {
      "max_rain_prob": 88,
      "risk_level": "HIGH"
    }
  },
  "Uyo, Akwa Ibom, Nigeria": {
    "timestamp": 1773931222.3436518,
    "data": {
      "max_rain_prob": 83,
      "risk_level": "HIGH"
    }
  },
  "Yola, Adamawa, Nigeria": {
    "timestamp": 1773931222.5725937,
    "data": {
      "max_rain_prob": 0,
      "risk_level": "LOW"
    }
  },
  "Awka, Anambra, Nigeria": {
    "timestamp": 1773931222.8127604,
    "data": {
      "max_rain_prob": 80,
      "risk_level": "HIGH"
    }
  },
  "Yenagoa, Bayelsa, Nigeria": {
    "timestamp": 1773931223.048538,
    "data": {
      "max_rain_prob": 71,
      "risk_level": "HIGH"
    }
  },
  "Makurdi, Benue, Nigeria": {
    "timestamp": 1773931223.2778118,
    "data": {
      "max_rain_prob": 0,
      "risk_level": "LOW"
    }
  },
  "Calabar, Cross River, Nigeria": {
    "timestamp": 1773931223.5340216,
    "data": {
      "max_rain_prob": 83,
      "risk_level": "HIGH"
    }
  },
  "Asaba, Delta, Nigeria": {
    "timestamp": 1773931223.7758274,
    "data": {
      "max_rain_prob": 59,
      "risk_level": "MODERATE"
    }
  },
  "Benin City, Edo, Nigeria": {
    "timestamp": 1773931224.1566975,
    "data": {
      "max_rain_prob": 4,
      "risk_level": "LOW"
    }
  },
  "Ado Ekiti, Ekiti, Nigeria": {
    "timestamp": 1773931224.398038,
    "data": {
      "max_rain_prob": 0,
      "risk_level": "LOW"
    }
  },
  "Enugu, Enugu, Nigeria": {
    "timestamp": 1773931224.6241689,
    "data": {
      "max_rain_prob": 68,
      "risk_level": "MODERATE"
    }
  },
  "Dutse, Jigawa, Nigeria": {
    "timestamp": 1773931224.8591223,
    "data": {
      "max_rain_prob": 0,
      "risk_level": "LOW"
    }
  },
  "Kaduna, Kaduna, Nigeria": {
    "timestamp": 1773931225.1039484,
    "data": {
      "max_rain_prob": 0,
      "risk_level": "LOW"
    }
  },
  "Kano, Kano, Nigeria": {
    "timestamp": 1773931225.36534,
    "data": {
      "max_rain_prob": 0,
      "risk_level": "LOW"
    }
  },
  "Birnin Kebbi, Kebbi, Nigeria": {
    "timestamp": 1773931225.6050766,
    "data": {
      "max_rain_prob": 0,
      "risk_level": "LOW"
    }
  },
  "Lokoja, Kogi, Nigeria": {
    "timestamp": 1773931225.8392522,
    "data": {
      "max_rain_prob": 0,
      "risk_level": "LOW"
    }
  },
  "Ilorin, Kwara, Nigeria": {
    "timestamp": 1773931226.0583537,
    "data": {
      "max_rain_prob": 0,
      "risk_level": "LOW"
    }
  },
  "Ikeja, Lagos, Nigeria": {
    "timestamp": 1773931226.2808151,
    "data": {
      "max_rain_prob": 0,
      "risk_level": "LOW"
    }
  },
  "Owerri, Imo, Nigeria": {
    "timestamp": 1773931226.4917986,
    "data": {
      "max_rain_prob": 88,
      "risk_level": "HIGH"
    }
  },
  "Abeokuta, Ogun, Nigeria": {
    "timestamp": 1773931226.7371807,
    "data": {
      "max_rain_prob": 0,
      "risk_level": "LOW"
    }
  },
  "Sagamu, Ogun State, Nigeria": {
    "timestamp": 1773931226.9872198,
    "data": {
      "max_rain_prob": 0,
      "risk_level": "LOW"
    }
  },
  "Akure, Ondo, Nigeria": {
    "timestamp": 1773931227.238689,
    "data": {
      "max_rain_prob": 0,
      "risk_level": "LOW"
    }
  },
  "Osogbo, Osun, Nigeria": {
    "timestamp": 1773931227.4726446,
    "data": {
      "max_rain_prob": 0,
      "risk_level": "LOW"
    }
  },
  "Jos, Plateau, Nigeria": {
    "timestamp": 1773931227.7252932,
    "data": {
      "max_rain_prob": 0,
      "risk_level": "LOW"
    }
  },
  "Port Harcourt, Rivers, Nigeria": {
    "timestamp": 1773931227.9489539,
    "data": {
      "max_rain_prob": 67,
      "risk_level": "MODERATE"
    }
  },
  "Ibadan, Oyo, Nigeria": {
    "timestamp": 1773931228.1798542,
    "data": {
      "max_rain_prob": 0,
      "risk_level": "LOW"
    }
  },
  "Jalingo, Taraba, Nigeria": {
    "timestamp": 1773931228.4226174,
    "data": {
      "max_rain_prob": 0,
      "risk_level": "LOW"
    }
  }
}