{
  "Umuahia, Abia, Nigeria": {
    "timestamp": 1775103407.1834788,
    "data": {
      "max_rain_prob": 77,
      "risk_level": "HIGH"
    }
  },
  "Uyo, Akwa Ibom, Nigeria": {
    "timestamp": 1775103407.5965137,
    "data": {
      "max_rain_prob": 96,
      "risk_level": "HIGH"
    }
  },
  "Yola, Adamawa, Nigeria": {
    "timestamp": 1775103407.9713833,
    "data": {
      "max_rain_prob": 22,
      "risk_level": "LOW"
    }
  },
  "Awka, Anambra, Nigeria": {
    "timestamp": 1775103408.3351498,
    "data": {
      "max_rain_prob": 97,
      "risk_level": "HIGH"
    }
  },
  "Yenagoa, Bayelsa, Nigeria": {
    "timestamp": 1775103408.7014463,
    "data": {
      "max_rain_prob": 100,
      "risk_level": "HIGH"
    }
  },
  "Makurdi, Benue, Nigeria": {
    "timestamp": 1775103409.0924964,
    "data": {
      "max_rain_prob": 85,
      "risk_level": "HIGH"
    }
  },
  "Calabar, Cross River, Nigeria": {
    "timestamp": 1775103409.4588811,
    "data": {
      "max_rain_prob": 100,
      "risk_level": "HIGH"
    }
  },
  "Asaba, Delta, Nigeria": {
    "timestamp": 1775103409.8269017,
    "data": {
      "max_rain_prob": 96,
      "risk_level": "HIGH"
    }
  },
  "Benin City, Edo, Nigeria": {
    "timestamp": 1775103410.19594,
    "data": {
      "max_rain_prob": 90,
      "risk_level": "HIGH"
    }
  },
  "Ado Ekiti, Ekiti, Nigeria": {
    "timestamp": 1775103410.5612662,
    "data": {
      "max_rain_prob": 68,
      "risk_level": "MODERATE"
    }
  },
  "Enugu, Enugu, Nigeria": {
    "timestamp": 1775103410.93124,
    "data": {
      "max_rain_prob": 100,
      "risk_level": "HIGH"
    }
  },
  "Dutse, Jigawa, Nigeria": {
    "timestamp": 1775103411.3109086,
    "data": {
      "max_rain_prob": 0,
      "risk_level": "LOW"
    }
  },
  "Kaduna, Kaduna, Nigeria": {
    "timestamp": 1775103411.6840646,
    "data": {
      "max_rain_prob": 0,
      "risk_level": "LOW"
    }
  },
  "Kano, Kano, Nigeria": {
    "timestamp": 1775103412.0505345,
    "data": {
      "max_rain_prob": 0,
      "risk_level": "LOW"
    }
  },
  "Birnin Kebbi, Kebbi, Nigeria": {
    "timestamp": 1775103412.4674888,
    "data": {
      "max_rain_prob": 0,
      "risk_level": "LOW"
    }
  },
  "Lokoja, Kogi, Nigeria": {
    "timestamp": 1775103412.8347507,
    "data": {
      "max_rain_prob": 69,
      "risk_level": "MODERATE"
    }
  },
  "Ilorin, Kwara, Nigeria": {
    "timestamp": 1775103413.244375,
    "data": {
      "max_rain_prob": 32,
      "risk_level": "LOW"
    }
  },
  "Ikeja, Lagos, Nigeria": {
    "timestamp": 1775103413.6585045,
    "data": {
      "max_rain_prob": 59,
      "risk_level": "MODERATE"
    }
  },
  "Owerri, Imo, Nigeria": {
    "timestamp": 1775103414.030043,
    "data": {
      "max_rain_prob": 78,
      "risk_level": "HIGH"
    }
  },
  "Abeokuta, Ogun, Nigeria": {
    "timestamp": 1775103414.3987935,
    "data": {
      "max_rain_prob": 46,
      "risk_level": "MODERATE"
    }
  },
  "Sagamu, Ogun State, Nigeria": {
    "timestamp": 1775103414.7603989,
    "data": {
      "max_rain_prob": 65,
      "risk_level": "MODERATE"
    }
  },
  "Akure, Ondo, Nigeria": {
    "timestamp": 1775103415.1245518,
    "data": {
      "max_rain_prob": 89,
      "risk_level": "HIGH"
    }
  },
  "Osogbo, Osun, Nigeria": {
    "timestamp": 1775103415.4924135,
    "data": {
      "max_rain_prob": 20,
      "risk_level": "LOW"
    }
  },
  "Jos, Plateau, Nigeria": {
    "timestamp": 1775103415.8608773,
    "data": {
      "max_rain_prob": 7,
      "risk_level": "LOW"
    }
  },
  "Port Harcourt, Rivers, Nigeria": {
    "timestamp": 1775103416.230905,
    "data": {
      "max_rain_prob": 96,
      "risk_level": "HIGH"
    }
  },
  "Ibadan, Oyo, Nigeria": {
    "timestamp": 1775103416.5961463,
    "data": {
      "max_rain_prob": 39,
      "risk_level": "LOW"
    }
  },
  "Jalingo, Taraba, Nigeria": {
    "timestamp": 1775103416.9692695,
    "data": {
      "max_rain_prob": 88,
      "risk_level": "HIGH"
    }
  }
}