{
  "Umuahia, Abia, Nigeria": {
    "timestamp": 1776164093.9606774,
    "data": {
      "max_rain_prob": 91,
      "risk_level": "HIGH"
    }
  },
  "Uyo, Akwa Ibom, Nigeria": {
    "timestamp": 1776164094.1263838,
    "data": {
      "max_rain_prob": 64,
      "risk_level": "MODERATE"
    }
  },
  "Yola, Adamawa, Nigeria": {
    "timestamp": 1776164094.3117857,
    "data": {
      "max_rain_prob": 0,
      "risk_level": "LOW"
    }
  },
  "Awka, Anambra, Nigeria": {
    "timestamp": 1776164094.4961777,
    "data": {
      "max_rain_prob": 47,
      "risk_level": "MODERATE"
    }
  },
  "Yenagoa, Bayelsa, Nigeria": {
    "timestamp": 1776164094.679279,
    "data": {
      "max_rain_prob": 65,
      "risk_level": "MODERATE"
    }
  },
  "Makurdi, Benue, Nigeria": {
    "timestamp": 1776164094.857009,
    "data": {
      "max_rain_prob": 69,
      "risk_level": "MODERATE"
    }
  },
  "Calabar, Cross River, Nigeria": {
    "timestamp": 1776164095.0260832,
    "data": {
      "max_rain_prob": 56,
      "risk_level": "MODERATE"
    }
  },
  "Asaba, Delta, Nigeria": {
    "timestamp": 1776164095.2039583,
    "data": {
      "max_rain_prob": 32,
      "risk_level": "LOW"
    }
  },
  "Benin City, Edo, Nigeria": {
    "timestamp": 1776164095.3726225,
    "data": {
      "max_rain_prob": 33,
      "risk_level": "LOW"
    }
  },
  "Ado Ekiti, Ekiti, Nigeria": {
    "timestamp": 1776164095.546576,
    "data": {
      "max_rain_prob": 74,
      "risk_level": "HIGH"
    }
  },
  "Enugu, Enugu, Nigeria": {
    "timestamp": 1776164095.7191057,
    "data": {
      "max_rain_prob": 71,
      "risk_level": "HIGH"
    }
  },
  "Dutse, Jigawa, Nigeria": {
    "timestamp": 1776164095.888964,
    "data": {
      "max_rain_prob": 0,
      "risk_level": "LOW"
    }
  },
  "Kaduna, Kaduna, Nigeria": {
    "timestamp": 1776164096.0572453,
    "data": {
      "max_rain_prob": 25,
      "risk_level": "LOW"
    }
  },
  "Kano, Kano, Nigeria": {
    "timestamp": 1776164096.275393,
    "data": {
      "max_rain_prob": 0,
      "risk_level": "LOW"
    }
  },
  "Birnin Kebbi, Kebbi, Nigeria": {
    "timestamp": 1776164096.4508128,
    "data": {
      "max_rain_prob": 20,
      "risk_level": "LOW"
    }
  },
  "Lokoja, Kogi, Nigeria": {
    "timestamp": 1776164096.6339962,
    "data": {
      "max_rain_prob": 50,
      "risk_level": "MODERATE"
    }
  },
  "Ilorin, Kwara, Nigeria": {
    "timestamp": 1776164096.8138418,
    "data": {
      "max_rain_prob": 51,
      "risk_level": "MODERATE"
    }
  },
  "Ikeja, Lagos, Nigeria": {
    "timestamp": 1776164096.996061,
    "data": {
      "max_rain_prob": 20,
      "risk_level": "LOW"
    }
  },
  "Owerri, Imo, Nigeria": {
    "timestamp": 1776164097.169312,
    "data": {
      "max_rain_prob": 69,
      "risk_level": "MODERATE"
    }
  },
  "Abeokuta, Ogun, Nigeria": {
    "timestamp": 1776164097.3451688,
    "data": {
      "max_rain_prob": 38,
      "risk_level": "LOW"
    }
  },
  "Sagamu, Ogun State, Nigeria": {
    "timestamp": 1776164097.5156746,
    "data": {
      "max_rain_prob": 40,
      "risk_level": "MODERATE"
    }
  },
  "Akure, Ondo, Nigeria": {
    "timestamp": 1776164097.68741,
    "data": {
      "max_rain_prob": 58,
      "risk_level": "MODERATE"
    }
  },
  "Osogbo, Osun, Nigeria": {
    "timestamp": 1776164097.8678968,
    "data": {
      "max_rain_prob": 76,
      "risk_level": "HIGH"
    }
  },
  "Jos, Plateau, Nigeria": {
    "timestamp": 1776164098.054437,
    "data": {
      "max_rain_prob": 24,
      "risk_level": "LOW"
    }
  },
  "Port Harcourt, Rivers, Nigeria": {
    "timestamp": 1776164098.2243676,
    "data": {
      "max_rain_prob": 64,
      "risk_level": "MODERATE"
    }
  },
  "Ibadan, Oyo, Nigeria": {
    "timestamp": 1776164098.3958278,
    "data": {
      "max_rain_prob": 46,
      "risk_level": "MODERATE"
    }
  },
  "Jalingo, Taraba, Nigeria": {
    "timestamp": 1776164098.569582,
    "data": {
      "max_rain_prob": 40,
      "risk_level": "MODERATE"
    }
  }
}