{
  "generated_at": "2026-05-09T07:29:20.188468+00:00",
  "locations": [
    {
      "place": "Umuahia, Abia, Nigeria",
      "temp": 25.45,
      "feels_like": 26.43,
      "humidity": 91,
      "wind_speed": 1.72,
      "clouds": 100,
      "description": "Overcast clouds",
      "rain_probability": 100,
      "risk": "HIGH"
    },
    {
      "place": "Uyo, Akwa Ibom, Nigeria",
      "temp": 26.12,
      "feels_like": 26.12,
      "humidity": 91,
      "wind_speed": 0.9,
      "clouds": 98,
      "description": "Light rain",
      "rain_probability": 88,
      "risk": "HIGH"
    },
    {
      "place": "Yola, Adamawa, Nigeria",
      "temp": 31.61,
      "feels_like": 33.44,
      "humidity": 49,
      "wind_speed": 4.55,
      "clouds": 4,
      "description": "Clear sky",
      "rain_probability": 0,
      "risk": "LOW"
    },
    {
      "place": "Awka, Anambra, Nigeria",
      "temp": 26.26,
      "feels_like": 26.26,
      "humidity": 86,
      "wind_speed": 2.02,
      "clouds": 90,
      "description": "Overcast clouds",
      "rain_probability": 81,
      "risk": "HIGH"
    },
    {
      "place": "Yenagoa, Bayelsa, Nigeria",
      "temp": 26.72,
      "feels_like": 29.86,
      "humidity": 89,
      "wind_speed": 0.54,
      "clouds": 100,
      "description": "Overcast clouds",
      "rain_probability": 97,
      "risk": "HIGH"
    },
    {
      "place": "Makurdi, Benue, Nigeria",
      "temp": 28.24,
      "feels_like": 31.74,
      "humidity": 74,
      "wind_speed": 3.39,
      "clouds": 41,
      "description": "Scattered clouds",
      "rain_probability": 0,
      "risk": "LOW"
    },
    {
      "place": "Calabar, Cross River, Nigeria",
      "temp": 25.95,
      "feels_like": 25.95,
      "humidity": 92,
      "wind_speed": 0.65,
      "clouds": 100,
      "description": "Overcast clouds",
      "rain_probability": 94,
      "risk": "HIGH"
    },
    {
      "place": "Asaba, Delta, Nigeria",
      "temp": 26.9,
      "feels_like": 30.07,
      "humidity": 86,
      "wind_speed": 1.84,
      "clouds": 98,
      "description": "Overcast clouds",
      "rain_probability": 81,
      "risk": "HIGH"
    },
    {
      "place": "Benin City, Edo, Nigeria",
      "temp": 25.4,
      "feels_like": 26.5,
      "humidity": 96,
      "wind_speed": 0.41,
      "clouds": 100,
      "description": "Overcast clouds",
      "rain_probability": 93,
      "risk": "HIGH"
    },
    {
      "place": "Ado Ekiti, Ekiti, Nigeria",
      "temp": 23.71,
      "feels_like": 24.51,
      "humidity": 91,
      "wind_speed": 2.04,
      "clouds": 100,
      "description": "Overcast clouds",
      "rain_probability": 31,
      "risk": "LOW"
    },
    {
      "place": "Enugu, Enugu, Nigeria",
      "temp": 26.29,
      "feels_like": 26.29,
      "humidity": 84,
      "wind_speed": 2.87,
      "clouds": 100,
      "description": "Overcast clouds",
      "rain_probability": 63,
      "risk": "MODERATE"
    },
    {
      "place": "Dutse, Jigawa, Nigeria",
      "temp": 28.75,
      "feels_like": 27.98,
      "humidity": 35,
      "wind_speed": 2.54,
      "clouds": 5,
      "description": "Clear sky",
      "rain_probability": 0,
      "risk": "LOW"
    },
    {
      "place": "Kaduna, Kaduna, Nigeria",
      "temp": 26.14,
      "feels_like": 26.14,
      "humidity": 64,
      "wind_speed": 2.99,
      "clouds": 98,
      "description": "Overcast clouds",
      "rain_probability": 0,
      "risk": "LOW"
    },
    {
      "place": "Kano, Kano, Nigeria",
      "temp": 28.61,
      "feels_like": 28.3,
      "humidity": 41,
      "wind_speed": 2.81,
      "clouds": 0,
      "description": "Clear sky",
      "rain_probability": 0,
      "risk": "LOW"
    },
    {
      "place": "Birnin Kebbi, Kebbi, Nigeria",
      "temp": 30.16,
      "feels_like": 31.98,
      "humidity": 54,
      "wind_speed": 5.75,
      "clouds": 0,
      "description": "Clear sky",
      "rain_probability": 0,
      "risk": "LOW"
    },
    {
      "place": "Lokoja, Kogi, Nigeria",
      "temp": 26.25,
      "feels_like": 26.25,
      "humidity": 82,
      "wind_speed": 1.43,
      "clouds": 100,
      "description": "Overcast clouds",
      "rain_probability": 3,
      "risk": "LOW"
    },
    {
      "place": "Ilorin, Kwara, Nigeria",
      "temp": 25.35,
      "feels_like": 26.13,
      "humidity": 84,
      "wind_speed": 3.13,
      "clouds": 100,
      "description": "Overcast clouds",
      "rain_probability": 0,
      "risk": "LOW"
    },
    {
      "place": "Ikeja, Lagos, Nigeria",
      "temp": 27.37,
      "feels_like": 31.06,
      "humidity": 84,
      "wind_speed": 2.81,
      "clouds": 100,
      "description": "Overcast clouds",
      "rain_probability": 5,
      "risk": "LOW"
    },
    {
      "place": "Owerri, Imo, Nigeria",
      "temp": 25.69,
      "feels_like": 26.72,
      "humidity": 92,
      "wind_speed": 1.04,
      "clouds": 100,
      "description": "Overcast clouds",
      "rain_probability": 100,
      "risk": "HIGH"
    },
    {
      "place": "Abeokuta, Ogun, Nigeria",
      "temp": 25.64,
      "feels_like": 26.61,
      "humidity": 90,
      "wind_speed": 2.18,
      "clouds": 88,
      "description": "Overcast clouds",
      "rain_probability": 21,
      "risk": "LOW"
    },
    {
      "place": "Sagamu, Ogun State, Nigeria",
      "temp": 26.15,
      "feels_like": 26.15,
      "humidity": 92,
      "wind_speed": 1.47,
      "clouds": 96,
      "description": "Overcast clouds",
      "rain_probability": 21,
      "risk": "LOW"
    },
    {
      "place": "Akure, Ondo, Nigeria",
      "temp": 24.25,
      "feels_like": 25.16,
      "humidity": 93,
      "wind_speed": 1.55,
      "clouds": 100,
      "description": "Overcast clouds",
      "rain_probability": 63,
      "risk": "MODERATE"
    },
    {
      "place": "Osogbo, Osun, Nigeria",
      "temp": 24.02,
      "feels_like": 24.96,
      "humidity": 95,
      "wind_speed": 1.99,
      "clouds": 100,
      "description": "Overcast clouds",
      "rain_probability": 49,
      "risk": "MODERATE"
    },
    {
      "place": "Jos, Plateau, Nigeria",
      "temp": 25.04,
      "feels_like": 25.06,
      "humidity": 56,
      "wind_speed": 1.14,
      "clouds": 36,
      "description": "Scattered clouds",
      "rain_probability": 0,
      "risk": "LOW"
    },
    {
      "place": "Port Harcourt, Rivers, Nigeria",
      "temp": 27.43,
      "feels_like": 31.09,
      "humidity": 83,
      "wind_speed": 1.56,
      "clouds": 100,
      "description": "Moderate rain",
      "rain_probability": 99,
      "risk": "HIGH"
    },
    {
      "place": "Ibadan, Oyo, Nigeria",
      "temp": 24.61,
      "feels_like": 25.58,
      "humidity": 94,
      "wind_speed": 2.06,
      "clouds": 98,
      "description": "Overcast clouds",
      "rain_probability": 51,
      "risk": "MODERATE"
    },
    {
      "place": "Jalingo, Taraba, Nigeria",
      "temp": 29.63,
      "feels_like": 32.9,
      "humidity": 64,
      "wind_speed": 4.1,
      "clouds": 54,
      "description": "Broken clouds",
      "rain_probability": 0,
      "risk": "LOW"
    }
  ]
}