{
  "generated_at": "2026-05-01T14:45:01.458072+00:00",
  "locations": [
    {
      "place": "Umuahia, Abia, Nigeria",
      "temp": 32.95,
      "feels_like": 37.38,
      "humidity": 54,
      "wind_speed": 2.5,
      "clouds": 81,
      "description": "Light rain",
      "rain_probability": 27,
      "risk": "LOW"
    },
    {
      "place": "Uyo, Akwa Ibom, Nigeria",
      "temp": 32.51,
      "feels_like": 37.97,
      "humidity": 59,
      "wind_speed": 2.43,
      "clouds": 100,
      "description": "Overcast clouds",
      "rain_probability": 39,
      "risk": "LOW"
    },
    {
      "place": "Yola, Adamawa, Nigeria",
      "temp": 41.51,
      "feels_like": 38.99,
      "humidity": 12,
      "wind_speed": 1.93,
      "clouds": 5,
      "description": "Clear sky",
      "rain_probability": 0,
      "risk": "LOW"
    },
    {
      "place": "Awka, Anambra, Nigeria",
      "temp": 35.28,
      "feels_like": 38.39,
      "humidity": 42,
      "wind_speed": 1.31,
      "clouds": 24,
      "description": "Few clouds",
      "rain_probability": 0,
      "risk": "LOW"
    },
    {
      "place": "Yenagoa, Bayelsa, Nigeria",
      "temp": 32.83,
      "feels_like": 38.74,
      "humidity": 59,
      "wind_speed": 3.48,
      "clouds": 70,
      "description": "Broken clouds",
      "rain_probability": 28,
      "risk": "LOW"
    },
    {
      "place": "Makurdi, Benue, Nigeria",
      "temp": 38.91,
      "feels_like": 39.98,
      "humidity": 27,
      "wind_speed": 1.19,
      "clouds": 45,
      "description": "Scattered clouds",
      "rain_probability": 0,
      "risk": "LOW"
    },
    {
      "place": "Calabar, Cross River, Nigeria",
      "temp": 31.96,
      "feels_like": 36.98,
      "humidity": 60,
      "wind_speed": 2.95,
      "clouds": 100,
      "description": "Overcast clouds",
      "rain_probability": 56,
      "risk": "MODERATE"
    },
    {
      "place": "Asaba, Delta, Nigeria",
      "temp": 36.45,
      "feels_like": 39.34,
      "humidity": 38,
      "wind_speed": 1.46,
      "clouds": 34,
      "description": "Scattered clouds",
      "rain_probability": 0,
      "risk": "LOW"
    },
    {
      "place": "Benin City, Edo, Nigeria",
      "temp": 36.9,
      "feels_like": 39.86,
      "humidity": 37,
      "wind_speed": 2.18,
      "clouds": 87,
      "description": "Overcast clouds",
      "rain_probability": 11,
      "risk": "LOW"
    },
    {
      "place": "Ado Ekiti, Ekiti, Nigeria",
      "temp": 37.05,
      "feels_like": 36.28,
      "humidity": 24,
      "wind_speed": 2.28,
      "clouds": 77,
      "description": "Broken clouds",
      "rain_probability": 0,
      "risk": "LOW"
    },
    {
      "place": "Enugu, Enugu, Nigeria",
      "temp": 34.27,
      "feels_like": 37.34,
      "humidity": 45,
      "wind_speed": 2.18,
      "clouds": 9,
      "description": "Clear sky",
      "rain_probability": 0,
      "risk": "LOW"
    },
    {
      "place": "Dutse, Jigawa, Nigeria",
      "temp": 40.85,
      "feels_like": 36.99,
      "humidity": 5,
      "wind_speed": 5.68,
      "clouds": 1,
      "description": "Clear sky",
      "rain_probability": 0,
      "risk": "LOW"
    },
    {
      "place": "Kaduna, Kaduna, Nigeria",
      "temp": 40.31,
      "feels_like": 36.56,
      "humidity": 5,
      "wind_speed": 4.29,
      "clouds": 100,
      "description": "Overcast clouds",
      "rain_probability": 0,
      "risk": "LOW"
    },
    {
      "place": "Kano, Kano, Nigeria",
      "temp": 41.01,
      "feels_like": 36.98,
      "humidity": 4,
      "wind_speed": 5.94,
      "clouds": 3,
      "description": "Clear sky",
      "rain_probability": 0,
      "risk": "LOW"
    },
    {
      "place": "Birnin Kebbi, Kebbi, Nigeria",
      "temp": 42.7,
      "feels_like": 38.44,
      "humidity": 5,
      "wind_speed": 4.13,
      "clouds": 99,
      "description": "Overcast clouds",
      "rain_probability": 0,
      "risk": "LOW"
    },
    {
      "place": "Lokoja, Kogi, Nigeria",
      "temp": 39.48,
      "feels_like": 39.55,
      "humidity": 23,
      "wind_speed": 2.07,
      "clouds": 100,
      "description": "Overcast clouds",
      "rain_probability": 0,
      "risk": "LOW"
    },
    {
      "place": "Ilorin, Kwara, Nigeria",
      "temp": 40.48,
      "feels_like": 38.85,
      "humidity": 16,
      "wind_speed": 3.65,
      "clouds": 9,
      "description": "Clear sky",
      "rain_probability": 0,
      "risk": "LOW"
    },
    {
      "place": "Ikeja, Lagos, Nigeria",
      "temp": 32.94,
      "feels_like": 39.94,
      "humidity": 66,
      "wind_speed": 3.6,
      "clouds": 75,
      "description": "Broken clouds",
      "rain_probability": 0,
      "risk": "LOW"
    },
    {
      "place": "Owerri, Imo, Nigeria",
      "temp": 34.78,
      "feels_like": 38.71,
      "humidity": 46,
      "wind_speed": 2.37,
      "clouds": 45,
      "description": "Scattered clouds",
      "rain_probability": 5,
      "risk": "LOW"
    },
    {
      "place": "Abeokuta, Ogun, Nigeria",
      "temp": 38.97,
      "feels_like": 40.8,
      "humidity": 29,
      "wind_speed": 3.05,
      "clouds": 30,
      "description": "Scattered clouds",
      "rain_probability": 0,
      "risk": "LOW"
    },
    {
      "place": "Sagamu, Ogun State, Nigeria",
      "temp": 35.46,
      "feels_like": 40.19,
      "humidity": 46,
      "wind_speed": 4.33,
      "clouds": 61,
      "description": "Broken clouds",
      "rain_probability": 0,
      "risk": "LOW"
    },
    {
      "place": "Akure, Ondo, Nigeria",
      "temp": 36.83,
      "feels_like": 36.67,
      "humidity": 27,
      "wind_speed": 2.38,
      "clouds": 70,
      "description": "Broken clouds",
      "rain_probability": 0,
      "risk": "LOW"
    },
    {
      "place": "Osogbo, Osun, Nigeria",
      "temp": 38.42,
      "feels_like": 37.45,
      "humidity": 21,
      "wind_speed": 2.81,
      "clouds": 17,
      "description": "Few clouds",
      "rain_probability": 0,
      "risk": "LOW"
    },
    {
      "place": "Jos, Plateau, Nigeria",
      "temp": 34.88,
      "feels_like": 32.21,
      "humidity": 9,
      "wind_speed": 4.05,
      "clouds": 22,
      "description": "Few clouds",
      "rain_probability": 0,
      "risk": "LOW"
    },
    {
      "place": "Port Harcourt, Rivers, Nigeria",
      "temp": 31.25,
      "feels_like": 36.76,
      "humidity": 65,
      "wind_speed": 2.65,
      "clouds": 100,
      "description": "Light rain",
      "rain_probability": 36,
      "risk": "LOW"
    },
    {
      "place": "Ibadan, Oyo, Nigeria",
      "temp": 38.57,
      "feels_like": 39.41,
      "humidity": 27,
      "wind_speed": 2.35,
      "clouds": 37,
      "description": "Scattered clouds",
      "rain_probability": 0,
      "risk": "LOW"
    },
    {
      "place": "Jalingo, Taraba, Nigeria",
      "temp": 40.76,
      "feels_like": 38.66,
      "humidity": 14,
      "wind_speed": 2.61,
      "clouds": 2,
      "description": "Clear sky",
      "rain_probability": 0,
      "risk": "LOW"
    }
  ]
}